pvevti/__init__.py
pvevti/csvutil.py
pvevti/genutil.py
pvevti/jsonutil.py
pvevti/mf4util.py
pvevti/pdfutil.py
pvevti/prefs.json
pvevti-2025.8.28.0.dist-info/METADATA
pvevti-2025.8.28.0.dist-info/WHEEL
pvevti-2025.8.28.0.dist-info/licenses/LICENSE
pvevti-2025.8.28.0.dist-info/RECORD
