Metadata-Version: 2.4
Name: pvevti
Version: 2025.8.28.0
Summary: A package with utilities expressly for the VTI/PVE teams at DTNA.
Project-URL: Homepage, https://northamerica.daimlertruck.com/
Author-email: Dave Moroney <dave.moroney@daimlertruck.com>
License-Expression: MIT
License-File: LICENSE
Keywords: DTNA,Daimler,PVE,VTI
Classifier: Operating System :: OS Independent
Classifier: Programming Language :: Python :: 3
Requires-Python: >=3.9
Requires-Dist: contextily
Requires-Dist: geopandas
Requires-Dist: matplotlib
Requires-Dist: pandas
